{
  "_class": "shapeGroup",
  "clippingMaskMode": 0,
  "do_objectID": "5132D21A-D85A-4C5F-A2FE-0FEFF0605F7F",
  "exportOptions": {
    "_class": "exportOptions",
    "exportFormats": [
    ],
    "includedLayerIds": [
    ],
    "layerOptions": 0,
    "shouldTrim": false
  },
  "frame": {
    "_class": "rect",
    "constrainProportions": false,
    "height": 23.99999999999999,
    "width": 10.5,
    "x": 2.5,
    "y": 0
  },
  "hasClickThrough": false,
  "hasClippingMask": false,
  "isFlippedHorizontal": false,
  "isFlippedVertical": false,
  "isLocked": false,
  "isVisible": true,
  "layerListExpandedType": 0,
  "layers": [
    {
      "class": "shapePath",
      "id": "12A6577D-EF62-43C2-95B8-E8D96D64546F"
    },
    {
      "class": "shapePath",
      "id": "80220C1A-470E-458A-A7F1-AA2AAB96056E"
    }
  ],
  "name": "Fill 3",
  "nameIsFixed": false,
  "originalObjectID": "5132D21A-D85A-4C5F-A2FE-0FEFF0605F7F",
  "resizingConstraint": 63,
  "resizingType": 0,
  "rotation": 0,
  "shouldBreakMaskChain": false,
  "style": {
    "_class": "style",
    "endDecorationType": 0,
    "fills": [
      {
        "_class": "fill",
        "color": {
          "_class": "color",
          "alpha": 1,
          "blue": 0.1669353246688843,
          "green": 0.6813615560531616,
          "red": 0.9454328417778015
        },
        "fillType": 0,
        "isEnabled": true,
        "noiseIndex": 0,
        "noiseIntensity": 0,
        "patternFillType": 0,
        "patternTileScale": 1
      }
    ],
    "miterLimit": 10,
    "startDecorationType": 0
  },
  "userInfo": {
    "com.animaapp.stc-sketch-plugin": {
      "kModelPropertiesKey": {
      }
    }
  },
  "windingRule": 1
}