{
  "_class": "group",
  "do_objectID": "3D304E13-1E78-4567-B1F8-7E06A3FE663C",
  "exportOptions": {
    "_class": "exportOptions",
    "exportFormats": [
    ],
    "includedLayerIds": [
    ],
    "layerOptions": 0,
    "shouldTrim": false
  },
  "frame": {
    "_class": "rect",
    "constrainProportions": false,
    "height": 24,
    "width": 94,
    "x": 0,
    "y": 0
  },
  "hasClickThrough": false,
  "isFlippedHorizontal": false,
  "isFlippedVertical": false,
  "isLocked": false,
  "isVisible": true,
  "layerListExpandedType": 0,
  "layers": [
    {
      "class": "shapeGroup",
      "id": "E5DC1D7F-FC75-413E-B246-F23F2E4ABF49"
    },
    {
      "class": "text",
      "id": "C931A22E-E435-4D31-8B0C-1C1D49D5D7DB"
    },
    {
      "class": "symbolInstance",
      "id": "22D8D6C7-E49E-4206-A717-4E699720B2F4"
    }
  ],
  "name": "Labels/Status/Highlight",
  "nameIsFixed": true,
  "resizingConstraint": 63,
  "resizingType": 0,
  "rotation": 0,
  "shouldBreakMaskChain": false,
  "style": {
    "_class": "style",
    "endDecorationType": 0,
    "miterLimit": 10,
    "shadows": [
      {
        "_class": "shadow",
        "blurRadius": 0,
        "color": {
          "_class": "color",
          "alpha": 0.3,
          "blue": 0.2823529411764706,
          "green": 0.2823529411764706,
          "red": 0.2823529411764706
        },
        "contextSettings": {
          "_class": "graphicsContextSettings",
          "blendMode": 0,
          "opacity": 1
        },
        "isEnabled": false,
        "offsetX": 0,
        "offsetY": 1,
        "spread": 0
      }
    ],
    "startDecorationType": 0
  },
  "userInfo": {
    "com.animaapp.stc-sketch-plugin": {
      "kModelPropertiesKey": {
      }
    }
  }
}